turdshovel/__init__.py
turdshovel/__main__.py
turdshovel/_dlls/Microsoft.Bcl.AsyncInterfaces.dll
turdshovel/_dlls/Microsoft.Bcl.AsyncInterfaces.xml
turdshovel/_dlls/Microsoft.Diagnostics.NETCore.Client.dll
turdshovel/_dlls/Microsoft.Diagnostics.NETCore.Client.xml
turdshovel/_dlls/Microsoft.Diagnostics.Runtime.dll
turdshovel/_dlls/Microsoft.Diagnostics.Runtime.pdb
turdshovel/_dlls/Microsoft.Diagnostics.Runtime.xml
turdshovel/_dlls/System.Buffers.dll
turdshovel/_dlls/System.Buffers.xml
turdshovel/_dlls/System.Collections.Immutable.dll
turdshovel/_dlls/System.Collections.Immutable.xml
turdshovel/_dlls/System.Memory.dll
turdshovel/_dlls/System.Memory.xml
turdshovel/_dlls/System.Numerics.Vectors.dll
turdshovel/_dlls/System.Numerics.Vectors.xml
turdshovel/_dlls/System.Reflection.Metadata.dll
turdshovel/_dlls/System.Reflection.Metadata.xml
turdshovel/_dlls/System.Runtime.CompilerServices.Unsafe.dll
turdshovel/_dlls/System.Runtime.CompilerServices.Unsafe.xml
turdshovel/_dlls/System.Threading.Tasks.Extensions.dll
turdshovel/_dlls/System.Threading.Tasks.Extensions.xml
turdshovel/_nubia.py
turdshovel/_stubs/Microsoft/__init__.py
turdshovel/_stubs/Microsoft/Diagnostics/__init__.py
turdshovel/_stubs/Microsoft/Diagnostics/NETCore/__init__.py
turdshovel/_stubs/Microsoft/Diagnostics/NETCore/Client.py
turdshovel/_stubs/Microsoft/Diagnostics/Runtime/__init__.py
turdshovel/_stubs/Microsoft/Diagnostics/Runtime/DacInterface.py
turdshovel/_stubs/Microsoft/Diagnostics/Runtime/DataReaders/__init__.py
turdshovel/_stubs/Microsoft/Diagnostics/Runtime/DataReaders/Implementation.py
turdshovel/_stubs/Microsoft/Diagnostics/Runtime/Implementation.py
turdshovel/_stubs/Microsoft/Diagnostics/Runtime/Utilities.py
turdshovel/_stubs/Microsoft/Diagnostics/Runtime/Windows.py
turdshovel/_stubs/System/__init__.py
turdshovel/_stubs/System/Buffers/__init__.py
turdshovel/_stubs/System/Buffers/Binary.py
turdshovel/_stubs/System/Buffers/Text.py
turdshovel/_stubs/System/Collections/__init__.py
turdshovel-0.3.dist-info/entry_points.txt
turdshovel-0.3.dist-info/LICENSE
turdshovel-0.3.dist-info/WHEEL
turdshovel-0.3.dist-info/METADATA
turdshovel-0.3.dist-info/RECORD
